Metadata-Version: 2.1
Name: ClarkePark
Version: 0.1.6
Summary: Clarke and Park Transforms
Home-page: https://clarkepark.readthedocs.io/
Author: Marco Polo Jacome Toss
Author-email: jacometoss@outlook.com
License: GPL-3.0
Project-URL: Documentation, https://clarkepark.readthedocs.io/
Project-URL: Source, https://github.com/jacometoss/ClarkePark
Project-URL: Funding, https://ko-fi.com/jacometoss
Project-URL: Forum, https://k-denveloper.blogspot.com/
Project-URL: Bug Tracker, https://github.com/jacometoss/ClarkePark/issues
Keywords: Clarke and Park Transforms,Inverse Park transform,transforms,Clark,Park
Platform: UNKNOWN
Classifier: License :: OSI Approved :: GNU Affero General Public License v3
Classifier: Programming Language :: Python
Classifier: Programming Language :: Python :: 3
Classifier: Programming Language :: Python :: 3.5
Classifier: Programming Language :: Python :: 3.6
Classifier: Programming Language :: Python :: 3.7
Classifier: Programming Language :: Python :: 3.8
Classifier: Programming Language :: Python :: 3.9
Classifier: Operating System :: Microsoft :: Windows
Classifier: Operating System :: POSIX :: Linux
Classifier: Topic :: Software Development :: Libraries :: Python Modules
Classifier: Topic :: Scientific/Engineering :: Physics
Classifier: Topic :: Scientific/Engineering :: Mathematics
Classifier: Topic :: Utilities 
Requires-Python: >=3.5
